pynoverb/__init__.py
pynoverb/__main__.py
pynoverb/load_hrtf_mit_kemar.py
pynoverb/pynoverb.py
pynoverb/wavio.py
pynoverb/hrtf/mit_kemar/H-10e000a.wav
pynoverb/hrtf/mit_kemar/H-10e005a.wav
pynoverb/hrtf/mit_kemar/H-10e010a.wav
pynoverb/hrtf/mit_kemar/H-10e015a.wav
pynoverb/hrtf/mit_kemar/H-10e020a.wav
pynoverb/hrtf/mit_kemar/H-10e025a.wav
pynoverb/hrtf/mit_kemar/H-10e030a.wav
pynoverb/hrtf/mit_kemar/H-10e035a.wav
pynoverb/hrtf/mit_kemar/H-10e040a.wav
pynoverb/hrtf/mit_kemar/H-10e045a.wav
pynoverb/hrtf/mit_kemar/H-10e050a.wav
pynoverb/hrtf/mit_kemar/H-10e055a.wav
pynoverb/hrtf/mit_kemar/H-10e060a.wav
pynoverb/hrtf/mit_kemar/H-10e065a.wav
pynoverb/hrtf/mit_kemar/H-10e070a.wav
pynoverb/hrtf/mit_kemar/H-10e075a.wav
pynoverb/hrtf/mit_kemar/H-10e080a.wav
pynoverb/hrtf/mit_kemar/H-10e085a.wav
pynoverb/hrtf/mit_kemar/H-10e090a.wav
pynoverb/hrtf/mit_kemar/H-10e095a.wav
pynoverb/hrtf/mit_kemar/H-10e100a.wav
pynoverb/hrtf/mit_kemar/H-10e105a.wav
pynoverb/hrtf/mit_kemar/H-10e110a.wav
pynoverb/hrtf/mit_kemar/H-10e115a.wav
pynoverb/hrtf/mit_kemar/H-10e120a.wav
pynoverb/hrtf/mit_kemar/H-10e125a.wav
pynoverb/hrtf/mit_kemar/H-10e130a.wav
pynoverb/hrtf/mit_kemar/H-10e135a.wav
pynoverb/hrtf/mit_kemar/H-10e140a.wav
pynoverb/hrtf/mit_kemar/H-10e145a.wav
pynoverb/hrtf/mit_kemar/H-10e150a.wav
pynoverb/hrtf/mit_kemar/H-10e155a.wav
pynoverb/hrtf/mit_kemar/H-10e160a.wav
pynoverb/hrtf/mit_kemar/H-10e165a.wav
pynoverb/hrtf/mit_kemar/H-10e170a.wav
pynoverb/hrtf/mit_kemar/H-10e175a.wav
pynoverb/hrtf/mit_kemar/H-10e180a.wav
pynoverb/hrtf/mit_kemar/H-20e000a.wav
pynoverb/hrtf/mit_kemar/H-20e005a.wav
pynoverb/hrtf/mit_kemar/H-20e010a.wav
pynoverb/hrtf/mit_kemar/H-20e015a.wav
pynoverb/hrtf/mit_kemar/H-20e020a.wav
pynoverb/hrtf/mit_kemar/H-20e025a.wav
pynoverb/hrtf/mit_kemar/H-20e030a.wav
pynoverb/hrtf/mit_kemar/H-20e035a.wav
pynoverb/hrtf/mit_kemar/H-20e040a.wav
pynoverb/hrtf/mit_kemar/H-20e045a.wav
pynoverb/hrtf/mit_kemar/H-20e050a.wav
pynoverb/hrtf/mit_kemar/H-20e055a.wav
pynoverb-0.0.1.dist-info/LICENSE
pynoverb-0.0.1.dist-info/METADATA
pynoverb-0.0.1.dist-info/WHEEL
pynoverb-0.0.1.dist-info/top_level.txt
pynoverb-0.0.1.dist-info/RECORD
