Metadata-Version: 2.1
Name: pynoverb
Version: 0.0.1
Summary: Impulse responses creation for room reverberation
Home-page: https://github.com/odoare/pynoverb
Author: Olivier Doaré
Author-email: <olivier.doare@ensta-paris.fr>
License: UNKNOWN
Keywords: Python,Binaural processing,Signal processing,Artificial reverberation
Platform: UNKNOWN
Classifier: Development Status :: 3 - Alpha
Classifier: Programming Language :: Python :: 3
License-File: LICENSE
Requires-Dist: numba
Requires-Dist: numpy
